scrapling/__init__.py
scrapling/cli.py
scrapling/parser.py
scrapling/py.typed
scrapling/core/__init__.py
scrapling/core/_html_utils.py
scrapling/core/_shell_signatures.py
scrapling/core/_types.py
scrapling/core/ai.py
scrapling/core/custom_types.py
scrapling/core/mixins.py
scrapling/core/shell.py
scrapling/core/storage.py
scrapling/core/translator.py
scrapling/core/utils/__init__.py
scrapling/core/utils/_shell.py
scrapling/core/utils/_utils.py
scrapling/engines/__init__.py
scrapling/engines/constants.py
scrapling/engines/static.py
scrapling/engines/_browsers/__init__.py
scrapling/engines/_browsers/_base.py
scrapling/engines/_browsers/_config_tools.py
scrapling/engines/_browsers/_controllers.py
scrapling/engines/_browsers/_page.py
scrapling/engines/_browsers/_stealth.py
scrapling/engines/_browsers/_types.py
scrapling/engines/_browsers/_validators.py
scrapling/engines/toolbelt/__init__.py
scrapling/engines/toolbelt/convertor.py
scrapling/engines/toolbelt/custom.py
scrapling/engines/toolbelt/fingerprints.py
scrapling/engines/toolbelt/navigation.py
scrapling/engines/toolbelt/bypasses/navigator_plugins.js
scrapling/engines/toolbelt/bypasses/notification_permission.js
scrapling/engines/toolbelt/bypasses/playwright_fingerprint.js
scrapling/engines/toolbelt/bypasses/screen_props.js
scrapling/engines/toolbelt/bypasses/webdriver_fully.js
scrapling/engines/toolbelt/bypasses/window_chrome.js
scrapling/fetchers/__init__.py
scrapling/fetchers/chrome.py
scrapling/fetchers/requests.py
scrapling/fetchers/stealth_chrome.py
scrapling-0.3.13.dist-info/licenses/LICENSE
scrapling-0.3.13.dist-info/METADATA
scrapling-0.3.13.dist-info/WHEEL
scrapling-0.3.13.dist-info/entry_points.txt
scrapling-0.3.13.dist-info/top_level.txt
scrapling-0.3.13.dist-info/RECORD
