Metadata-Version: 2.4
Name: scrapling
Version: 0.3.13
Summary: Scrapling is an undetectable, powerful, flexible, high-performance Python library that makes Web Scraping easy and effortless as it should be!
Home-page: https://github.com/D4Vinci/Scrapling
Author: Karim Shoair
Author-email: Karim Shoair <karim.shoair@pm.me>
Maintainer-email: Karim Shoair <karim.shoair@pm.me>
License: BSD 3-Clause License
Project-URL: Homepage, https://github.com/D4Vinci/Scrapling
Project-URL: Changelog, https://github.com/D4Vinci/Scrapling/releases
Project-URL: Documentation, https://scrapling.readthedocs.io/en/latest/
Project-URL: Repository, https://github.com/D4Vinci/Scrapling
Project-URL: Bug Tracker, https://github.com/D4Vinci/Scrapling/issues
Keywords: web-scraping,scraping,automation,browser-automation,data-extraction,html-parsing,undetectable,playwright,selenium-alternative,web-crawler,browser,crawling
Classifier: Operating System :: OS Independent
Classifier: Development Status :: 4 - Beta
Classifier: Intended Audience :: Developers
Classifier: Intended Audience :: Information Technology
Classifier: License :: OSI Approved :: BSD License
Classifier: Natural Language :: English
Classifier: Topic :: Internet :: WWW/HTTP
Classifier: Topic :: Internet :: WWW/HTTP :: Browsers
Classifier: Topic :: Text Processing :: Markup
Classifier: Topic :: Text Processing :: Markup :: HTML
Classifier: Topic :: Scientific/Engineering :: Artificial Intelligence
Classifier: Topic :: Software Development :: Libraries
Classifier: Topic :: Software Development :: Libraries :: Python Modules
Classifier: Programming Language :: Python :: 3
Classifier: Programming Language :: Python :: 3 :: Only
Classifier: Programming Language :: Python :: 3.10
Classifier: Programming Language :: Python :: 3.11
Classifier: Programming Language :: Python :: 3.12
Classifier: Programming Language :: Python :: 3.13
Classifier: Programming Language :: Python :: Implementation :: CPython
Classifier: Typing :: Typed
Requires-Python: >=3.10
License-File: LICENSE
Requires-Dist: lxml>=6.0.2
Requires-Dist: cssselect>=1.3.0
Requires-Dist: orjson>=3.11.5
Requires-Dist: tldextract>=5.3.1
Provides-Extra: fetchers
Requires-Dist: click>=8.3.0; extra == "fetchers"
Requires-Dist: curl_cffi>=0.14.0; extra == "fetchers"
Requires-Dist: playwright==1.56.0; extra == "fetchers"
Requires-Dist: patchright==1.56.0; extra == "fetchers"
Requires-Dist: browserforge>=1.2.1; extra == "fetchers"
Requires-Dist: msgspec>=0.20.0; extra == "fetchers"
Provides-Extra: ai
Requires-Dist: mcp>=1.24.0; extra == "ai"
Requires-Dist: markdownify>=1.2.0; extra == "ai"
Requires-Dist: scrapling[fetchers]; extra == "ai"
Provides-Extra: shell
Requires-Dist: IPython>=8.37; extra == "shell"
Requires-Dist: markdownify>=1.2.0; extra == "shell"
Requires-Dist: scrapling[fetchers]; extra == "shell"
Provides-Extra: all
Requires-Dist: scrapling[ai,shell]; extra == "all"
Dynamic: license-file
